{
  "ServiceName": "aiglossarypro-main-apps-api",
  "SourceConfiguration": {
    "CodeRepository": {
      "RepositoryUrl": "https://github.com/pranaysuyash/aiglossarypro",
      "SourceCodeVersion": {
        "Type": "BRANCH",
        "Value": "main"
      },
      "SourceDirectory": "/apps/api",
      "CodeConfiguration": {
        "ConfigurationSource": "REPOSITORY",
        "CodeConfigurationValues": {
          "Runtime": "NODEJS_18"
        }
      }
    },
    "AutoDeploymentsEnabled": true,
    "AuthenticationConfiguration": {
      "ConnectionArn": "arn:aws:apprunner:us-east-1:927289246324:connection/github-connection/47d0187c36184de9b0c586c0c44ba86d"
    }
  }
}